telesm/__init__.py
telesm/__main__.py
telesm/ai.py
telesm/db.py
telesm/decorators.py
telesm/env.py
telesm/main.py
telesm/operations.py
telesm-0.2.5.dist-info/LICENSE
telesm-0.2.5.dist-info/METADATA
telesm-0.2.5.dist-info/WHEEL
telesm-0.2.5.dist-info/entry_points.txt
telesm-0.2.5.dist-info/top_level.txt
telesm-0.2.5.dist-info/RECORD
