Metadata-Version: 2.1
Name: telesm
Version: 0.2.5
Summary: A command-line dictionary app using WordNet and OpenAI
Home-page: https://github.com/pedrambehroozi/telesm
Author: Pedram Behroozi
Author-email: pedrambehroozi@gmail.com
Classifier: Programming Language :: Python :: 3
License-File: LICENSE
Requires-Dist: nltk
Requires-Dist: requests
Requires-Dist: python-dotenv
